{
    "Objects": [
        {
            "ObjectID": "^SPHERESHAPE",
            "Position": [
                -0.1817578673362732,
                0.6015148758888245,
                0.1811116337776184
            ],
            "Up": [
                -2.1914599912520316e-08,
                0.17999999225139618,
                6.386375025613233e-05
            ],
            "At": [
                0.00018134906713385135,
                0.00035479862708598375,
                -0.9999999403953552
            ],
            "Timestamp": 1651921460,
            "UserData": 14
        },
        {
            "ObjectID": "^SPHERESHAPE",
            "Position": [
                -0.1817578673362732,
                0.6015148758888245,
                -0.1812846064567566
            ],
            "Up": [
                -2.1914599912520316e-08,
                0.17999999225139618,
                6.386375025613233e-05
            ],
            "At": [
                0.00018134906713385135,
                0.00035479862708598375,
                -0.9999999403953552
            ],
            "Timestamp": 1651921460,
            "UserData": 14
        },
        {
            "ObjectID": "^SPHERESHAPE",
            "Position": [
                0.18168741464614868,
                0.6015148758888245,
                0.1811116337776184
            ],
            "Up": [
                -2.1914599912520316e-08,
                0.17999999225139618,
                6.386375025613233e-05
            ],
            "At": [
                0.00018134906713385135,
                0.00035479862708598375,
                -0.9999999403953552
            ],
            "Timestamp": 1651921460,
            "UserData": 14
        },
        {
            "ObjectID": "^SPHERESHAPE",
            "Position": [
                -0.36331456899642944,
                0.3619594871997833,
                -0.3621165156364441
            ],
            "Up": [
                -2.191082693059343e-08,
                0.17999999225139618,
                6.384229345712811e-05
            ],
            "At": [
                0.00018134906713385135,
                0.00035467944690026343,
                -0.9999999403953552
            ],
            "Timestamp": 1651921460,
            "UserData": 14
        },
        {
            "ObjectID": "^SPHERESHAPE",
            "Position": [
                -0.00020116567611694336,
                0.3619594871997833,
                -0.3621165156364441
            ],
            "Up": [
                -2.191082693059343e-08,
                0.17999999225139618,
                6.384229345712811e-05
            ],
            "At": [
                0.00018134906713385135,
                0.00035467944690026343,
                -0.9999999403953552
            ],
            "Timestamp": 1651921460,
            "UserData": 14
        },
        {
            "ObjectID": "^SPHERESHAPE",
            "Position": [
                0.3635759949684143,
                0.3619594871997833,
                -0.3621165156364441
            ],
            "Up": [
                -2.191082693059343e-08,
                0.17999999225139618,
                6.384229345712811e-05
            ],
            "At": [
                0.00018134906713385135,
                0.00035467944690026343,
                -0.9999999403953552
            ],
            "Timestamp": 1651921460,
            "UserData": 14
        },
        {
            "ObjectID": "^SPHERESHAPE",
            "Position": [
                0.18168741464614868,
                0.6015148758888245,
                -0.1812846064567566
            ],
            "Up": [
                -2.1914599912520316e-08,
                0.17999999225139618,
                6.386375025613233e-05
            ],
            "At": [
                0.00018134906713385135,
                0.00035479862708598375,
                -0.9999999403953552
            ],
            "Timestamp": 1651921460,
            "UserData": 14
        },
        {
            "ObjectID": "^SPHERESHAPE",
            "Position": [
                -3.331899642944336e-05,
                0.8399153351783752,
                -7.123446266632527e-05
            ],
            "Up": [
                -2.191082693059343e-08,
                0.17999999225139618,
                6.384229345712811e-05
            ],
            "At": [
                0.00018134906713385135,
                0.00035467944690026343,
                -0.9999999403953552
            ],
            "Timestamp": 1651921460,
            "UserData": 14
        },
        {
            "ObjectID": "^SPHERESHAPE",
            "Position": [
                0.3635759949684143,
                0.3619595170021057,
                -0.00043742451816797256
            ],
            "Up": [
                -6.412906805053353e-05,
                0.17999999225139618,
                -2.8189847967041715e-07
            ],
            "At": [
                0.9999999403953552,
                0.0003562728816177696,
                0.0001811538531910628
            ],
            "Timestamp": 1651921460,
            "UserData": 14
        },
        {
            "ObjectID": "^SPHERESHAPE",
            "Position": [
                0.3635759949684143,
                0.3619595468044281,
                0.3626912236213684
            ],
            "Up": [
                -6.412906805053353e-05,
                0.17999999225139618,
                -2.8189847967041715e-07
            ],
            "At": [
                0.9999999403953552,
                0.0003562728816177696,
                0.0001811538531910628
            ],
            "Timestamp": 1651921460,
            "UserData": 14
        },
        {
            "ObjectID": "^SPHERESHAPE",
            "Position": [
                -0.36331456899642944,
                0.3619595170021057,
                -0.00043742451816797256
            ],
            "Up": [
                -2.1914599912520316e-08,
                0.17999999225139618,
                6.386375025613233e-05
            ],
            "At": [
                0.00018134906713385135,
                0.00035479862708598375,
                -0.9999999403953552
            ],
            "Timestamp": 1651921460,
            "UserData": 14
        },
        {
            "ObjectID": "^SPHERESHAPE",
            "Position": [
                -0.00020116567611694336,
                0.3619595170021057,
                -0.00043742451816797256
            ],
            "Up": [
                -2.1914599912520316e-08,
                0.17999999225139618,
                6.386375025613233e-05
            ],
            "At": [
                0.00018134906713385135,
                0.00035479862708598375,
                -0.9999999403953552
            ],
            "Timestamp": 1651921460,
            "UserData": 14
        },
        {
            "ObjectID": "^SPHERESHAPE",
            "Position": [
                -0.36331456899642944,
                0.3619595468044281,
                0.3626912236213684
            ],
            "Up": [
                -2.1914599912520316e-08,
                0.17999999225139618,
                6.386375025613233e-05
            ],
            "At": [
                0.00018134906713385135,
                0.00035479862708598375,
                -0.9999999403953552
            ],
            "Timestamp": 1651921460,
            "UserData": 14
        },
        {
            "ObjectID": "^SPHERESHAPE",
            "Position": [
                -0.00020116567611694336,
                0.3619595468044281,
                0.3626912236213684
            ],
            "Up": [
                -2.1914599912520316e-08,
                0.17999999225139618,
                6.386375025613233e-05
            ],
            "At": [
                0.00018134906713385135,
                0.00035479862708598375,
                -0.9999999403953552
            ],
            "Timestamp": 1651921460,
            "UserData": 14
        },
        {
            "ObjectID": "^S_PALLET",
            "Position": [
                -6.616115570068359e-06,
                0.13190847635269165,
                5.090431386634009e-06
            ],
            "Up": [
                -0.00035615282831713557,
                0.9999985098838806,
                -1.625752133804781e-06
            ],
            "At": [
                0.9999999403953552,
                0.00035615364322438836,
                0.00018151146650779992
            ],
            "Timestamp": 1651922191,
            "UserData": 0
        }
    ],
    "timestamp": 1684029555,
    "BaseVersion": 5
}